{
  "fr-FR": {
    "Oh no...": "",
    "You do not have access to this page or resource.": "",
    "Forbidden": "",
    "Go to Homepage": ""
  },
  "es-ES": {
    "Oh no...": "",
    "You do not have access to this page or resource.": "",
    "Forbidden": "",
    "Go to Homepage": ""
  },
  "ja-JP": {
    "Oh no...": "",
    "You do not have access to this page or resource.": "",
    "Forbidden": "",
    "Go to Homepage": ""
  },
  "pt-BR": {
    "Oh no...": "",
    "You do not have access to this page or resource.": "",
    "Forbidden": "",
    "Go to Homepage": ""
  }
}
